Workbook

Sheet Résumé
A1: Plan définitif PharmaGeno — suivi
A2: Mémoire « A Deep Learning based Webtool for Mutation-Aware Drug Recommendation » · plan du 12 octobre 2026, mis à jour le 15 octobre 2026
A4: Date de dépôt (hypothèse, à corriger) | B4: 46338 | C4: Hypothèse : « un mois » à partir du 12 oct. La date exacte n'est pas confirmée.
A5: Jours restants avant le dépôt | B5: =B4-TODAY() -> 28
A6: Indicateurs
A7: Tâches au total | B7: =COUNTA(Plan!$A$2:$A$200) -> 43
A8: Faites | B8: =COUNTIF(Plan!$J$2:$J$200,"Fait") -> 17
A9: En cours | B9: =COUNTIF(Plan!$J$2:$J$200,"En cours") -> 5
A10: Bloquées | B10: =COUNTIF(Plan!$J$2:$J$200,"Bloqué") -> 0
A11: Coupées | B11: =COUNTIF(Plan!$J$2:$J$200,"Coupé") -> 0
A12: Avancement (faites / total) | B12: =IF(B7=0,0,B8/B7) -> 0.39534884
A13: Faites ET vérifiées | B13: =COUNTIFS(Plan!$J$2:$J$200,"Fait",Plan!$K$2:$K$200,"Vérifié") -> 17
A14: Faites mais non vérifiées | B14: =B8-B13 -> 0
A15: Faites avec une sauvegarde manquante | B15: =SUMPRODUCT((Plan!$J$2:$J$200="Fait")*(((Plan!$L$2:$L$200="Non")+(Plan!$M$2:$M$200="Non")+(Plan!$N$2:$N$200="Non")+(Plan!$O$2:$O$200="Non"))>0)) -> 1
A17: Avancement par semaine
A18: Semaine | B18: Période | C18: Tâches | D18: Faites | E18: Avancement
A19: S1 | B19: 13–19 oct. | C19: =COUNTIF(Plan!$B$2:$B$200,A19) -> 19 | D19: =COUNTIFS(Plan!$B$2:$B$200,A19,Plan!$J$2:$J$200,"Fait") -> 11 | E19: =IF(C19=0,0,D19/C19) -> 0.57894737
A20: S2 | B20: 20–26 oct. | C20: =COUNTIF(Plan!$B$2:$B$200,A20) -> 9 | D20: =COUNTIFS(Plan!$B$2:$B$200,A20,Plan!$J$2:$J$200,"Fait") -> 4 | E20: =IF(C20=0,0,D20/C20) -> 0.44444444
A21: S3 | B21: 27 oct.–2 nov. | C21: =COUNTIF(Plan!$B$2:$B$200,A21) -> 8 | D21: =COUNTIFS(Plan!$B$2:$B$200,A21,Plan!$J$2:$J$200,"Fait") -> 2 | E21: =IF(C21=0,0,D21/C21) -> 0.25
A22: S4 | B22: 3–9 nov. | C22: =COUNTIF(Plan!$B$2:$B$200,A22) -> 4 | D22: =COUNTIFS(Plan!$B$2:$B$200,A22,Plan!$J$2:$J$200,"Fait") -> 0 | E22: =IF(C22=0,0,D22/C22) -> 0
A23: Marge | B23: 10–12 nov. | C23: =COUNTIF(Plan!$B$2:$B$200,A23) -> 3 | D23: =COUNTIFS(Plan!$B$2:$B$200,A23,Plan!$J$2:$J$200,"Fait") -> 0 | E23: =IF(C23=0,0,D23/C23) -> 0
A26: Comment remplir
A27: Cellules à modifier : dans l'onglet Plan, les colonnes Statut, Vérifié et les 4 colonnes de sauvegarde (texte bleu). Dans cet onglet, la date de dépôt (cellule jaune).
A28: Exemple : une tâche terminée et contrôlée → Statut = Fait, Vérifié = Vérifié, WSL / Windows / GitHub / Drive = Oui.
A29: Une ligne devient rouge dans les colonnes de sauvegarde quand la tâche est Fait mais qu'un support est encore à Non.
A30: « Vérifié » veut dire contrôlé sur le résultat lui-même, pas seulement exécuté. Ordre de sauvegarde : WSL → Windows → GitHub → Drive.
A31: Les dates de l'onglet Plan sont les bornes de la semaine, pas des échéances précises.
A32: « À confirmer » dans les colonnes de sauvegarde : support non vu dans cette session ; non compté dans « sauvegarde manquante » ; à remplacer par Oui ou Non.
A33: Sources citées dans le plan (liens non rouverts pour ce fichier)
A34: PyPGx | B34: https://github.com/sbslee/pypgx
A35: PharmCAT | B35: https://pharmcat.clinpgx.org
A36: CPIC | B36: https://cpicpgx.org/guidelines/
A37: OMS ATC/DDD | B37: https://www.whocc.no/atc_ddd_index/
A38: GeT-RM (CDC) | B38: https://www.cdc.gov/lab-quality/php/get-rm/reference-materials.html

Sheet Plan
A1: ID | B1: Semaine | C1: Période | D1: Phase | E1: Tâche | F1: Livrable | G1: Qui | H1: Début | I1: Fin | J1: Statut | K1: Vérifié | L1: WSL | M1: Windows | N1: GitHub | O1: Drive | P1: Coupable (ordre) | Q1: Remarques
A2: T01 | B2: S1 | C2: 13–19 oct. | D2: P0 Cadrage | E2: GO sur le plan définitif | F2: Accord écrit de Mouna | G2: Mouna | H2: 46308 | I2: 46314 | J2: À faire | K2: Non vérifié | L2: Sans objet | M2: Sans objet | N2: Sans objet | O2: Sans objet | P2: Jamais | Q2: Point de départ de tout le reste · 15 oct. : accord non confirmé dans cette conversation ; le travail suit tes « ok » (protocole v7, modèles retenus)
A3: T02 | B3: S1 | C3: 13–19 oct. | D3: P0 Cadrage | E3: Relire controle_regles_v2.csv et remplir verdict_Mouna / commentaire | F3: controle_regles_v2.csv annoté | G3: Mouna | H3: 46308 | I3: 46314 | J3: À faire | K3: Non vérifié | L3: Non | M3: Non | N3: Non | O3: Non | P3: Jamais | Q3: Par défaut, les lignes sans verdict restent exclues de l'entraînement · 15 oct. : toujours en attente
A4: T03 | B4: S1 | C4: 13–19 oct. | D4: P0 Cadrage | E4: Joindre phenotype_drug_dataset_FINAL.csv, drug_fingerprints_v2.pkl et drug_smiles.csv (sinon tester le téléchargement depuis le Drive) | F4: 3 fichiers disponibles pour Claude | G4: Mouna | H4: 46308 | I4: 46314 | J4: Fait | K4: Vérifié | L4: Sans objet | M4: Sans objet | N4: Sans objet | O4: Sans objet | P4: Jamais | Q4: Le téléchargement Drive des gros fichiers n'est pas vérifié · 15 oct. : drug_fingerprints_v2.pkl (437 médicaments, 518 colonnes) et phenotype_drug_dataset_FINAL.csv reçus et utilisés ; drug_smiles.csv non rouvert dans cette session
A5: T04 | B5: S1 | C5: 13–19 oct. | D5: P0 Cadrage | E5: Lire predict_v4.py, app_v4.py, vcf_parser.py et train_fp.py | F5: Constat écrit de l'état du code | G5: Claude | H5: 46308 | I5: 46314 | J5: En cours | K5: Non vérifié | L5: Sans objet | M5: Sans objet | N5: Sans objet | O5: Sans objet | P5: Jamais | Q5: Non lus à ce jour · 15 oct. : vcf_parser.py (liste de rsID, sans allèles étoiles), predict_phenotype.py (ancien DL v5) et generate_report.py (rapport PDF reportlab) survolés ; predict_v4.py, app_v4.py et train_fp.py non lus
A6: T05 | B6: S1 | C6: 13–19 oct. | D6: P1 Lecteur VCF | E6: Tester PyPGx sur patient_multi_gene.vcf, patient_sans_mutation.vcf, patient_dpyd.vcf et pharmacat.example2.vcf | F6: Tableau valeur par gène pour chaque VCF | G6: Claude | H6: 46308 | I6: 46314 | J6: Fait | K6: Vérifié | L6: À confirmer | M6: À confirmer | N6: À confirmer | O6: À confirmer | P6: Jamais | Q6: Peut devoir se faire chez Mouna si l'espace de Claude ne permet pas de lancer l'outil · 12 oct. : PyPGx 0.27.0 (GRCh38) testé sur 4 VCF + 2 VCF diagnostiques ; rapport P1_resultats_lecteur_VCF_12oct2026.md
A7: T06 | B7: S1 | C7: 13–19 oct. | D7: P1 Lecteur VCF | E7: Comparer le résultat à PharmCAT sur les mêmes VCF | F7: Tableau de concordance PyPGx / PharmCAT | G7: Claude | H7: 46308 | I7: 46314 | J7: Fait | K7: Vérifié | L7: À confirmer | M7: À confirmer | N7: À confirmer | O7: À confirmer | P7: Jamais | Q7: Nécessite Java et l'accès à l'outil · 12 oct. : PharmCAT 3.0.0 ; concordance 8 gènes sur 8 sur un VCF réel ; CYP2D6 « Unknown » chez PharmCAT depuis un VCF de SNP
A8: T07 | B8: S1 | C8: 13–19 oct. | D8: P1 Lecteur VCF | E8: Écrire vcf_to_profile.py : gène absent = référence (1,0), mais « non déterminé » pour CYP2D6, HLA-B et pour un VCF trop pauvre | F8: vcf_to_profile.py + tests sur les 4 VCF | G8: Claude | H8: 46308 | I8: 46314 | J8: À faire | K8: Non vérifié | L8: Non | M8: Non | N8: Non | O8: Non | P8: Jamais | Q8: Convention à confirmer sur l'outil retenu · 15 oct. : convention retenue par défaut = « non déterminé » si le gène n'est pas couvert ; vcf_to_profile.py pas encore écrit
A9: T08 | B9: S1 | C9: 13–19 oct. | D9: P2 Spécialités | E9: Table spécialité ↔ classe ATC (OMS) | F9: Table à valider par Mouna | G9: Claude | H9: 46308 | I9: 46314 | J9: En cours | K9: Non vérifié | L9: À confirmer | M9: À confirmer | N9: À confirmer | O9: À confirmer | P9: Jamais | Q9: Source : WHO ATC/DDD index · 13 oct. : tables livrées en brouillon (atc_mapping_medicaments_v1.csv, specialite_atc_v1.csv) ; validation de Mouna en attente (22 correspondances, 28 noms, 17 spécialités)
A10: T09 | B10: S1 | C10: 13–19 oct. | D10: P2 Spécialités | E10: Table des alternatives (regles_alternatives_v2.csv), dérivée du texte des guidelines | F10: regles_alternatives_v2.csv à valider | G10: Claude | H10: 46308 | I10: 46314 | J10: En cours | K10: Non vérifié | L10: À confirmer | M10: À confirmer | N10: À confirmer | O10: À confirmer | P10: Jamais | Q10: Sert à étiqueter STANDARD les alternatives nommées par les guidelines · 13 oct. : alternatives_atc4_v1.csv livré en brouillon, fondé sur les classes ATC (pas sur le texte des guidelines) ; équivalence clinique non affirmée ; validation en attente
A11: T10 | B11: S1 | C11: 13–19 oct. | D11: P3 Étiquettes v3 | E11: Corpus v3 : nouvelle colonne action (règles v2), STANDARD tiré des règles de phénotype normal, règles ambiguës exclues | F11: Corpus v3 (nouveau fichier, rien d'écrasé) | G11: Claude | H11: 46308 | I11: 46314 | J11: Fait | K11: Vérifié | L11: Oui | M11: Oui | N11: À confirmer | O11: À confirmer | P11: Jamais | Q11: Seule la colonne action est reconstruite · Corpus v3 croisé : 76 028 lignes, 1 379 profils réels, 76 médicaments (SHA256 d1cc932e…)
A12: T11 | B12: S1 | C12: 13–19 oct. | D12: P3 Étiquettes v3 | E12: Tests de référence : codéine, clopidogrel, oméprazole | F12: Rapport de tests | G12: Claude | H12: 46308 | I12: 46314 | J12: Fait | K12: Vérifié | L12: Oui | M12: Oui | N12: À confirmer | O12: À confirmer | P12: Jamais | Q12: corpus_v3_tests_reference.csv ; tests_reference_corpus_v3.py
A13: T12 | B13: S1 | C13: 13–19 oct. | D13: P3 Étiquettes v3 | E13: Rapport de couverture (gènes sans règle, médicaments sans empreinte : 93 sur 530) | F13: Rapport de couverture | G13: Claude | H13: 46308 | I13: 46314 | J13: Fait | K13: Vérifié | L13: Oui | M13: Oui | N13: À confirmer | O13: À confirmer | P13: Jamais | Q13: corpus_v3_couverture_par_medicament.csv et _par_origine.csv
... A30: T29 | B30: S3 | C30: 27 oct.–2 nov. | D30: P7 Rédaction | E30: Chapitre 4 (conception et implémentation) | F30: Chapitre 4 | G30: Mouna | H30: 46322 | I30: 46328 | J30: À faire | K30: Non vérifié | L30: Non | M30: Non | N30: Non | O30: Non | P30: Jamais | Q30: Contenu technique fourni par Claude ; reformulation par Mouna
A31: T30 | B31: S4 | C31: 3–9 nov. | D31: P6 Validation | E31: Tests de bout en bout sur les VCF de test | F31: Rapport de tests | G31: Claude | H31: 46329 | I31: 46335 | J31: À faire | K31: Non vérifié | L31: Non | M31: Non | N31: Non | O31: Non | P31: Jamais
A32: T31 | B32: S4 | C32: 3–9 nov. | D32: P6 Validation | E32: Validation GeT-RM sur un sous-ensemble | F32: Rapport de concordance | G32: Claude | H32: 46329 | I32: 46335 | J32: À faire | K32: Non vérifié | L32: Non | M32: Non | N32: Non | O32: Non | P32: 4 | Q32: Peut être réduite à quelques échantillons
A33: T32 | B33: S4 | C33: 3–9 nov. | D33: P7 Rédaction | E33: Chapitres 6 à 8 | F33: Chapitres 6 à 8 | G33: Mouna | H33: 46329 | I33: 46335 | J33: À faire | K33: Non vérifié | L33: Non | M33: Non | N33: Non | O33: Non | P33: Jamais | Q33: Contenu technique fourni par Claude ; reformulation par Mouna
A34: T33 | B34: S4 | C34: 3–9 nov. | D34: P6 Validation | E34: Sauvegarde des 4 supports : WSL → Windows → GitHub → Drive | F34: Dépôt à jour sur les 4 supports | G34: Mouna | H34: 46329 | I34: 46335 | J34: À faire | K34: Non vérifié | L34: Sans objet | M34: Sans objet | N34: Sans objet | O34: Sans objet | P34: Jamais | Q34: Cocher les colonnes de chaque tâche au fur et à mesure
A35: T34 | B35: Marge | C35: 10–12 nov. | D35: P7 Rédaction | E35: Aligner le §1.1 du chapitre 1 avec l'écran de l'application (1 à 4 médicaments, spécialité) | F35: §1.1 corrigé ou écart expliqué | G35: Mouna | H35: 46336 | I35: 46338 | J35: À faire | K35: Non vérifié | L35: Non | M35: Non | N35: Non | O35: Non | P35: Jamais | Q35: Partie validée : modification seulement avec accord de Mouna
A36: T35 | B36: Marge | C36: 10–12 nov. | D36: P7 Rédaction | E36: Relecture et mise en forme du mémoire | F36: Mémoire final | G36: Mouna | H36: 46336 | I36: 46338 | J36: À faire | K36: Non vérifié | L36: Non | M36: Non | N36: Non | O36: Non | P36: Jamais
A37: T36 | B37: Marge | C37: 10–12 nov. | D37: P7 Rédaction | E37: Dépôt du mémoire | F37: Dépôt | G37: Mouna | H37: 46336 | I37: 46338 | J37: À faire | K37: Non vérifié | L37: Sans objet | M37: Sans objet | N37: Sans objet | O37: Sans objet | P37: Jamais | Q37: Date supposée : voir Résumé
A38: T37 | B38: S1 | C38: 13–19 oct. | D38: P4 Entraînement | E38: Protocole commun v7 : ensemble final de 138 familles + 5 plis groupés par famille | F38: protocole_commun.py + decoupage_v7.csv | G38: Claude | H38: 46308 | I38: 46314 | J38: Fait | K38: Vérifié | L38: Oui | M38: Oui | N38: À confirmer | O38: Oui | P38: Jamais | Q38: Garde-fous de non-fuite dans le code ; 12 gènes en entrée (colonnes non constantes)
A39: T38 | B39: S1 | C39: 13–19 oct. | D39: P4 Entraînement | E39: Analyse des erreurs du DL v6 (essai exploratoire) | F39: analyse_erreurs_dl_v6.py + sortie texte | G39: Claude | H39: 46308 | I39: 46314 | J39: Fait | K39: Vérifié | L39: Oui | M39: Oui | N39: À confirmer | O39: Oui | P39: Jamais | Q39: A conduit à la variante film
A40: T39 | B40: S1 | C40: 13–19 oct. | D40: P4 Entraînement | E40: Évaluation finale unique (DL film_id, XGBoost id, RF id) sur les 138 familles | F40: modele_final_v7.py + resultats_final_v7/ (+ modèles pour l'application) | G40: Claude | H40: 46308 | I40: 46314 | J40: Fait | K40: Vérifié | L40: Oui | M40: Non | N40: Non | O40: Non | P40: Jamais | Q40: 15 oct. : F1 0,9993 / 0,9996 / 0,9968 ; verrou anti-réévaluation. SAUVEGARDE À FAIRE (Windows, GitHub, Drive)
A41: T40 | B41: S1 | C41: 13–19 oct. | D41: P3 Étiquettes v3 | E41: Contrôle de l'origine des valeurs constantes à 1,0 (phenotype_drug_dataset_complet_v2.csv) | F41: Constat écrit (conversation) | G41: Claude | H41: 46308 | I41: 46314 | J41: Fait | K41: Vérifié | L41: Sans objet | M41: Sans objet | N41: Sans objet | O41: Sans objet | P41: Jamais | Q41: 15 oct. : 1,0 = valeur par défaut dans les scripts ; fichier sans identifiant patient ; « normal » ou « non renseigné » non décidable
A42: T41 | B42: S1 | C42: 13–19 oct. | D42: P7 Rédaction | E42: Chapitres 1, 2 et 3 mis à jour (v2, v2, v3) | F42: Chapitre_1_…FINAL_v2.docx, Chapitre_2_…FINAL_v2.docx, Chapitre_3_…FINAL_v3.docx | G42: Claude | H42: 46308 | I42: 46314 | J42: Fait | K42: Vérifié | L42: À confirmer | M42: À confirmer | N42: À confirmer | O42: À confirmer | P42: Jamais | Q42: 15 oct. : fichiers validés et rendus ; RQ4 reformulée à confirmer par Mouna
A43: T42 | B43: S1 | C43: 13–19 oct. | D43: P7 Rédaction | E43: Chapitre 3 v4 : constantes à 1,0, résultats finaux, RQ5, film_id, ajouts après coup | F43: Chapitre_3_…FINAL_v4.docx | G43: Claude | H43: 46308 | I43: 46314 | J43: À faire | K43: Non vérifié | L43: Non | M43: Non | N43: Non | O43: Non | P43: Jamais | Q43: Une seule nouvelle version, sans renvois multiples
A44: T43 | B44: S1 | C44: 13–19 oct. | D44: P5 Application | E44: Discuter avec Pr. Ghedira la formulation de la contribution du DL (≈ XGBoost ; échec RQ5) | F44: Formulation validée | G44: Mouna | H44: 46308 | I44: 46314 | J44: À faire | K44: Non vérifié | L44: Sans objet | M44: Sans objet | N44: Sans objet | O44: Sans objet | P44: Jamais | Q44: À faire avant la rédaction du chapitre 5

Sheet Décisions
A1: ID | B1: Décision | C1: Statut | D1: Remarque
A2: D01 | B2: Plan définitif en phases P0 à P7 (calendrier du 13 oct. au 12 nov.) | C2: À valider | D2: GO attendu de Mouna
A3: D02 | B3: Lecteur de VCF : PyPGx, comparé à PharmCAT | C3: À valider | D3: Même lecteur pour l'entraînement et pour l'application · Testé le 12 oct. : 8 gènes sur 8 concordants avec PharmCAT sur un VCF réel (GRCh38) ; CYP2D6 non appelable depuis un VCF de SNP
A4: D03 | B4: Écran : 1 à 4 médicaments classés du meilleur au moins bon, profil combiné de tous les gènes | C4: À valider | D4: Jamais dix médicaments ou plus
A5: D04 | B5: Random Forest dans la comparaison des trois modèles | C5: Actée | D5: Jamais retiré en silence · Réalisé : RF évalué en CV et sur l'ensemble final
A6: D05 | B6: « Prédiction initiale » placée en fin de liste de coupes | C6: À valider | D6: Sens de la fonction non défini
A7: D06 | B7: Application autonome pilotée par le Deep Learning | C7: Actée | D7: Les guidelines servent aux étiquettes, à l'évaluation et aux références · 15 oct. : DL film_id ≈ XGBoost (final 0,9993 vs 0,9996) ; voir D18
A8: D07 | B8: Spécialité du médecin en entrée avec le VCF | C8: Actée | D8: Évite de balayer tous les médicaments
A9: D08 | B9: Bloc patient en langage clair, sans dose | C9: Actée | D9: Même résultat, expliqué simplement
A10: D09 | B10: Garder la formulation prudente du chapitre 1 | C10: Actée | D10: Pas de revendication « mieux que CPIC »
A11: D10 | B11: Gènes non lisibles (CYP2D6, HLA-B) : « non déterminés », indicateur en entrée du modèle | C11: Fixé par défaut | D11: Remplace le remplissage à 1,0
A12: D11 | B12: Prédiction sans guideline : affichée comme « prédiction du modèle, pas de guideline » | C12: Révisée | D12: Corrigeable · Remplacée par D17 : RQ5 montre 53–63 % d'EVITER manqués sur des médicaments inconnus
... A20: D19 | B20: Ensemble final évalué une seule fois par modèle (verrou) ; ses chiffres sont les chiffres officiels | C20: Actée | D20: Réalisé le 15 oct.

Sheet Coupes et risques
A1: Type | B1: Élément | C1: Détail
A2: Coupe n°1 | B2: Noms commerciaux dans la recherche | C2: Premier élément abandonné en cas de retard
A3: Coupe n°2 | B3: Fonction « prédiction initiale » | C3: Sens non défini
A4: Coupe n°3 | B4: Finition du PDF | C4: Une version minimale reste dans le périmètre
A5: Coupe n°4 | B5: Validation GeT-RM réduite à quelques échantillons
A6: Jamais coupé | B6: Étiquettes v3
A7: Jamais coupé | B7: Comparaison des trois modèles | C7: Si Random Forest n'est pas terminé : écrit « non réalisé »
A8: Jamais coupé | B8: RQ5 (médicaments non vus) | C8: Expérience décisive · Réalisée le 15 oct. : résultat négatif rapporté
A9: Jamais coupé | B9: Recommandation par spécialité
A10: Jamais coupé | B10: Chapitres du mémoire
A11: Limite | B11: Le Deep Learning peut ne pas battre XGBoost | C11: Constaté le 15 oct. : DL film_id 0,9993 contre XGBoost 0,9996 sur l'ensemble final (IC95 qui se recouvrent) ; rapporté tel quel
A12: Limite | B12: Exécution sur le WSL de Mouna | C12: Claude livre des scripts, Mouna confirme chaque commande
A13: Limite | B13: Lecteur de VCF | C13: Peut ne pas tourner dans l'espace de Claude ; test alors chez Mouna
A14: Limite | B14: Étiquettes dérivées de règles | C14: Les métriques classiques mesurent la fidélité aux règles ; l'apport du DL se juge sur RQ5, RQ1, RQ3, RQ6
A15: Limite | B15: Généralisation à des médicaments inconnus | C15: RQ5 : F1 0,48–0,59 et 53–63 % d'EVITER manqués ; l'application ne recommande que les 76 médicaments à règles
A16: Limite | B16: Contribution du DL | C16: Au niveau des règles et des arbres sur les médicaments connus ; formulation à discuter avec Pr. Ghedira
A17: Limite | B17: CYP2D6 depuis un VCF | C17: PharmCAT « Unknown » depuis un VCF de SNP ; « non déterminé » tant qu'un appel fiable n'est pas établi
A18: Limite | B18: Ensemble final | C18: Évalué une seule fois par modèle (verrou) ; aucun réglage possible après coup
A19: Limite | B19: Ancien fichier phenotype_drug_dataset_complet_v2.csv | C19: 1,0 est la valeur par défaut dans les scripts ; l'absence de variation et l'absence de donnée ne sont pas distinguables

Sheet Besoins
A1: ID | B1: Ce qu'il faut de Mouna | C1: Statut | D1: Remarque
A2: B01 | B2: GO sur le plan définitif | C2: À faire
A3: B02 | B3: Joindre FINAL.csv, drug_fingerprints_v2.pkl et drug_smiles.csv dans la conversation | C3: Fait | D3: Sinon Claude teste le téléchargement depuis le Drive · Fichiers reçus le 13–15 oct. (drug_smiles.csv non rouvert)
A4: B03 | B4: Verdicts dans controle_regles_v2.csv | C4: À faire | D4: Par défaut, lignes sans verdict exclues de l'entraînement
A5: B04 | B5: Confirmer la date exacte de dépôt | C5: À faire | D5: Hypothèse actuelle : 12 nov. 2026
A6: B05 | B6: Définir le sens de « comparer avec la prédiction initiale » | C6: À faire | D6: Reste en fin de liste de coupes
A7: B06 | B7: Sauvegarder les résultats finaux : resultats_final_v7/*, resultats_final_v7.log, modele_final_v7.py (sauvegarde.sh puis Drive : Results et scripts) | C7: À faire | D7: Glisser aussi les 6 fichiers RQ5 dans Drive
A8: B07 | B8: Valider ou changer les décisions fixées par défaut D14 à D18 | C8: À faire | D8: RQ4 reformulée, film_id, arbres sans réglage, 76 médicaments, moteur DL + XGBoost
A9: B08 | B9: Discuter avec Pr. Ghedira la formulation de la contribution du DL | C9: À faire | D9: DL ≈ XGBoost sur médicaments connus ; échec RQ5
A10: B09 | B10: Valider les tables ATC, spécialités et alternatives (P2) | C10: À faire | D10: 22 correspondances, 28 noms, 17 spécialités
A11: B10 | B11: Confirmer les 14 règles conditionnelles acceptées | C11: À faire | D11: Cités au chapitre 3
A12: B11 | B12: Nettoyer Drive Docs : doublons « (1) », corpus_v3_tests_reference.csv mal placé, ajouter Corpus_v3_rapport_13oct2026_v2.md | C12: À faire

Sheet Journal
A1: Rubrique | B1: Entrée
A2: Décisions validées | B2: Application autonome pilotée par le DL ; spécialité en entrée ; bloc patient ; formulation prudente du chapitre 1 ; protocole v7 (ensemble final de 138 familles, 5 plis groupés par famille, 12 gènes) ; évaluation finale unique par modèle ; film_id ajouté après coup et déclaré
A3: Décisions à valider | B3: RQ4 reformulée (empreinte contre identifiant) ; arbres sans réglage ; application limitée aux 76 médicaments à règles ; moteur DL film_id + second avis XGBoost ; formulation de la contribution du DL (avec Pr. Ghedira) ; convention « gène absent »
A4: Erreur à ne plus reproduire | B4: Redemander des points déjà tranchés
A5: Erreur à ne plus reproduire | B5: Afficher un résultat par gène comme résultat principal
A6: Erreur à ne plus reproduire | B6: Remplir un gène absent à 1,0 sans distinguer « non lu »
A7: Erreur à ne plus reproduire | B7: Dire « terminé » sans distinguer vérifié et non vérifié
A8: Erreur à ne plus reproduire | B8: Comparer l'exactitude seule (la classe majoritaire fait 0,74 sur médicaments inconnus)
A9: Erreur à ne plus reproduire | B9: Deviner un nom de colonne ou un chemin sans vérifier
A10: Erreur à ne plus reproduire | B10: Réévaluer l'ensemble final ou comparer des chiffres issus de protocoles différents
A11: Reste à faire | B11: Voir l'onglet Plan (T04, T07 à T09, T17 à T21, T24 à T36, T42, T43) et l'onglet Besoins. Priorité : sauvegarde des résultats finaux, vcf_to_profile.py, couche de recommandation, application, chapitre 3 v4, chapitres 4 à 8
A12: Sauvegarde | B12: Plan_PharmaGeno_15oct2026.xlsx remplace le plan du 12 oct. (ancien fichier conservé). Ordre : WSL → Windows → GitHub → Drive. « À confirmer » = sauvegarde non vue dans cette session
